SpeechToText/__init__.py
AtharvaTech_STT-0.1.dist-info/METADATA
AtharvaTech_STT-0.1.dist-info/WHEEL
AtharvaTech_STT-0.1.dist-info/top_level.txt
AtharvaTech_STT-0.1.dist-info/RECORD
