Metadata-Version: 2.1
Name: AtharvaTech-STT
Version: 0.1
Summary: This is Speech-To-Text Package created by Atharva Shinde
Author: Atharva Shinde
Author-email: atharvathehero07@gmail.com
